.gitignore
.version_last
LICENSE
MANIFEST.in
bld.bat
build.sh
header_fields.ods
meta.yaml
setup.py
doc/Makefile
doc/classes.rst
doc/conf.py
doc/curve.rst
doc/exposure.rst
doc/header.rst
doc/index.rst
doc/make.bat
doc/mask.rst
retired_code/fitfunction.py
retired_code/misc.py
retired_code/saspreview2d.py
retired_code/transform.py
retired_code/dataset/__init__.py
retired_code/dataset/attributealias.py
retired_code/dataset/dataset.py
sastool/__init__.py
sastool/libconfig.py
sastool.egg-info/PKG-INFO
sastool.egg-info/SOURCES.txt
sastool.egg-info/dependency_links.txt
sastool.egg-info/not-zip-safe
sastool.egg-info/requires.txt
sastool.egg-info/top_level.txt
sastool/classes/__init__.py
sastool/classes/beamtime.py
sastool/classes/common.py
sastool/classes/curve.py
sastool/classes/exposure.py
sastool/classes/exposure_plugin.py
sastool/classes/header.py
sastool/classes/header_plugin.py
sastool/classes/headerfields.py
sastool/classes/history.py
sastool/classes/mask.py
sastool/classes/scan.py
sastool/classes2/__init__.py
sastool/classes2/curve.py
sastool/classes2/exposure.py
sastool/classes2/header.py
sastool/classes2/loader.py
sastool/classes2/scan/__init__.py
sastool/classes2/scan/specfile.py
sastool/fitting/__init__.py
sastool/fitting/standalone.py
sastool/fitting/fitfunctions/__init__.py
sastool/fitting/fitfunctions/basic.py
sastool/fitting/fitfunctions/bilayers.py
sastool/fitting/fitfunctions/c_fitfunction.c
sastool/fitting/fitfunctions/c_fitfunction.pyx
sastool/fitting/fitfunctions/sasbasic.py
sastool/fitting/fitfunctions/saspolymer.py
sastool/fitting/fitfunctions/sasspecial.py
sastool/io/__init__.py
sastool/io/asa.py
sastool/io/b1.py
sastool/io/c_io.c
sastool/io/c_io.pyx
sastool/io/header.py
sastool/io/onedim.py
sastool/io/statistics.py
sastool/io/twodim.py
sastool/io/credo_cct/__init__.py
sastool/io/credo_cct/exposure.py
sastool/io/credo_cct/header.py
sastool/io/credo_cct/loader.py
sastool/io/credo_saxsctrl/__init__.py
sastool/io/credo_saxsctrl/exposure.py
sastool/io/credo_saxsctrl/header.py
sastool/io/credo_saxsctrl/loader.py
sastool/misc/__init__.py
sastool/misc/arithmetic.py
sastool/misc/basicfit.py
sastool/misc/easylsq.py
