Metadata-Version: 1.1
Name: sastool
Version: 1.0.4
Summary: Python macros for [A]SA(X|N)S data processing, fitting, plotting etc.
Home-page: http://github.com/awacha/sastool
Author: Andras Wacha
Author-email: awacha@gmail.com
License: BSD 3-clause
Keywords: saxs sans sas small-angle scattering x-ray neutron
Platform: UNKNOWN
Classifier: Development Status :: 4 - Beta
Classifier: Environment :: Console
Classifier: Intended Audience :: Science/Research
Classifier: License :: OSI Approved :: BSD License
Classifier: Natural Language :: English
Classifier: Operating System :: POSIX
Classifier: Operating System :: Microsoft :: Windows
Classifier: Operating System :: POSIX :: Linux
Classifier: Operating System :: MacOS
Classifier: Programming Language :: Python :: 3
